fucking_argparse/__init__.py
fucking_argparse/code_generate.py
fucking_argparse-0.0.3.dist-info/LICENCE
fucking_argparse-0.0.3.dist-info/METADATA
fucking_argparse-0.0.3.dist-info/WHEEL
fucking_argparse-0.0.3.dist-info/top_level.txt
fucking_argparse-0.0.3.dist-info/RECORD
