Metadata-Version: 2.1
Name: fucking-argparse
Version: 0.0.3
Summary: A dataclass generate library for Namespace object generated by argparse
Author-email: ss <huangzheng@shu.edu.cn>
Project-URL: Homepage, https://github.com/Shadowsight9/fucking-argparse
Requires-Python: >=3.9
License-File: LICENCE
